pyarmor/README.rst
pyarmor/__init__.py
pyarmor/benchmark.py
pyarmor/build_meta.py
pyarmor/cobuilder.py
pyarmor/config.py
pyarmor/license.tri
pyarmor/packer.py
pyarmor/product.key
pyarmor/project.py
pyarmor/protect_code.pt
pyarmor/protect_code2.pt
pyarmor/public.key
pyarmor/public_capsule.zip
pyarmor/pyarmor-deprecated.py
pyarmor/pyarmor-webui.py
pyarmor/pyarmor.py
pyarmor/pyimcore.py
pyarmor/pyshield.key
pyarmor/pyshield.lic
pyarmor/pytransform.py
pyarmor/reform.py
pyarmor/register.py
pyarmor/sppmode.py
pyarmor/utils.py
pyarmor/cli/__init__.py
pyarmor/cli/__main__.py
pyarmor/cli/batch.py
pyarmor/cli/bootstrap.py
pyarmor/cli/bug.py
pyarmor/cli/command.py
pyarmor/cli/config.py
pyarmor/cli/context.py
pyarmor/cli/core.data.1
pyarmor/cli/core.data.2
pyarmor/cli/core.data.3
pyarmor/cli/default.cfg
pyarmor/cli/docker.py
pyarmor/cli/generate.py
pyarmor/cli/hdinfo.py
pyarmor/cli/merge.py
pyarmor/cli/mixer.py
pyarmor/cli/model.py
pyarmor/cli/plugin.py
pyarmor/cli/project.py
pyarmor/cli/public_capsule.zip
pyarmor/cli/register.py
pyarmor/cli/repack.py
pyarmor/cli/resource.py
pyarmor/cli/shell.py
pyarmor/examples/README-ZH.md
pyarmor/examples/README.md
pyarmor/examples/build-for-exe.bat
pyarmor/examples/build-for-freeze.bat
pyarmor/examples/build-with-project.bat
pyarmor/examples/build-with-project.sh
pyarmor/examples/obfuscate-app.bat
pyarmor/examples/obfuscate-app.sh
pyarmor/examples/obfuscate-pkg.bat
pyarmor/examples/obfuscate-pkg.sh
pyarmor/examples/pack-obfuscated-scripts.bat
pyarmor/examples/pack-obfuscated-scripts.sh
pyarmor/examples/cx_Freeze/hello.py
pyarmor/examples/cx_Freeze/queens.py
pyarmor/examples/cx_Freeze/setup.py
pyarmor/examples/helloworld/foo.py
pyarmor/examples/py2exe/hello.py
pyarmor/examples/py2exe/queens.py
pyarmor/examples/py2exe/setup.py
pyarmor/examples/pybench/Arithmetic.py
pyarmor/examples/pybench/Calls.py
pyarmor/examples/pybench/CommandLine.py
pyarmor/examples/pybench/Constructs.py
pyarmor/examples/pybench/Dict.py
pyarmor-9.2.3.dist-info/LICENSE
pyarmor-9.2.3.dist-info/LICENSE-ZH
pyarmor-9.2.3.dist-info/LICENSE-ZH.7
pyarmor-9.2.3.dist-info/LICENSE.7
pyarmor-9.2.3.dist-info/METADATA
pyarmor-9.2.3.dist-info/WHEEL
pyarmor-9.2.3.dist-info/entry_points.txt
pyarmor-9.2.3.dist-info/top_level.txt
pyarmor-9.2.3.dist-info/RECORD
