Metadata-Version: 1.1
Name: pyarmor
Version: 9.2.3
Summary: A tool used to obfuscate python scripts, bind obfuscated scripts to fixed machine or expire obfuscated scripts.
Home-page: https://github.com/dashingsoft/pyarmor
Author: Jondy Zhao
Author-email: pyarmor@163.com
License: Free To Use But Restricted
Keywords: protect obfuscate encrypt obfuscation distribute
Platform: UNKNOWN
Classifier: Development Status :: 4 - Beta
Classifier: Intended Audience :: Developers
Classifier: Topic :: Software Development :: Build Tools
Classifier: Topic :: Utilities
Classifier: Topic :: Security
Classifier: Topic :: System :: Software Distribution
Classifier: License :: Free To Use But Restricted
Classifier: Operating System :: MacOS
Classifier: Operating System :: Microsoft :: Windows
Classifier: Operating System :: POSIX
Classifier: Programming Language :: Python :: 2
Classifier: Programming Language :: Python :: 3
